{
    "configurations": [
        {
            "name": "Linux",
            "includePath": [
                "${workspaceFolder}/**",
                "/usr/include/c++/15/**",
                "/usr/include/c++/15/backward",
                "/usr/include/**",
                "/usr/include/c++/15:/usr/include/"
            ],
            "defines": [],
            "compilerPath": "/usr/bin/g++",
            "cStandard": "c23",
            "cppStandard": "c++23",
            "intelliSenseMode": "linux-gcc-x64",
            "compilerArgs": [
                "-std=c++23",
                "-O2"
            ],
            "browse": {
                "path": [
                    "${workspaceFolder}",
                    "/usr/include/c++/15",
                    "/usr/include"
                ],
                "limitSymbolsToIncludedHeaders": true
            }
        }
    ],
    "version": 4
}